my_nalog/__init__.py
my_nalog/api.py
my_nalog/exceptions.py
my_nalog/models.py
my_nalog-0.2.0.dist-info/METADATA
my_nalog-0.2.0.dist-info/WHEEL
my_nalog-0.2.0.dist-info/top_level.txt
my_nalog-0.2.0.dist-info/RECORD
