Metadata-Version: 2.4
Name: my-nalog
Version: 0.2.0
Summary: Python client for lknpd.nalog.ru API
Home-page: https://github.com/S1qwy/my-nalog
Author: S1qwy
Author-email: amirhansuper75@gmail.com
Classifier: Programming Language :: Python :: 3
Classifier: License :: OSI Approved :: MIT License
Classifier: Operating System :: OS Independent
Requires-Python: >=3.7
Requires-Dist: requests>=2.25.0
Dynamic: author
Dynamic: author-email
Dynamic: classifier
Dynamic: description
Dynamic: description-content-type
Dynamic: home-page
Dynamic: requires-dist
Dynamic: requires-python
Dynamic: summary
